setup.py
NSX/MANIFEST.in
NSX/NSX_API.csv
NSX/__init__.py
NSX/check_manager.py
NSX/compute_manager.py
NSX/edge_deploy.py
NSX/fw_multi_object.py
NSX/general_request.py
NSX/import_nsx_info.py
NSX/lb_multi_object.py
NSX/license.py
NSX/log.py
NSX/manager_deploy.py
NSX/multi_object_create.py
NSX/nsx_script_log.txt
NSX/object_search.py
NSX/policy.py
NSX/profile.py
NSX/setup.py
NSX/vcenter_con.py
NSX/data/00.deploy_main-ferderation.py
NSX/data/00.deploy_main.py
NSX/data/01.deploy_LB.py
NSX/data/02.deploy_FW.py
NSX/data/NSX.txt
NSX/data/NSX.txt.1
NSX/data/__init__.py
NSX/data/config-AS.csv
NSX/data/config-site-a.csv
NSX/data/config-site-b.csv
NSX/data/config.csv
NSX/data/config.xlsx
NSX/data/config_ebgp.csv
NSX/data/dfw.csv
NSX/data/dfw.xlsx
NSX/data/fw.xlsx
NSX/data/group.csv
NSX/data/gw.csv
NSX/data/gw.xlsx
NSX/data/lb.csv
NSX/data/lb.xlsx
NSX/data/lb_del.csv
NSX/data/service.csv
NSX/data/service.xlsx
NSX/data/sslcrt.crt
NSX/data/sslcsr.csr
NSX/data/sslkey.key
NSX/data/~$config.xlsx
seung_test.egg-info/PKG-INFO
seung_test.egg-info/SOURCES.txt
seung_test.egg-info/dependency_links.txt
seung_test.egg-info/requires.txt
seung_test.egg-info/top_level.txt