Metadata-Version: 2.1
Name: seung-test
Version: 0.1.1.9
Summary: This package is a Python script for deploying and configuring NSX-T TESTLAB. Made by seungwang.
Home-page: UNKNOWN
Author: Seung Wang Kim
Author-email: seungwangkim@gmail.com
License: MIT
Platform: UNKNOWN
Requires-Python: >=3.9
